chartops/__init__.py
chartops/chartops.py
chartops/cli.py
chartops/common.py
chartops/folium.py
chartops-0.3.0.dist-info/licenses/LICENSE
chartops-0.3.0.dist-info/METADATA
chartops-0.3.0.dist-info/WHEEL
chartops-0.3.0.dist-info/entry_points.txt
chartops-0.3.0.dist-info/top_level.txt
chartops-0.3.0.dist-info/RECORD
