Metadata-Version: 2.4
Name: Chartops
Version: 0.3.0
Summary: Python Boilerplate contains all the boilerplate you need to create a Python package.
Author-email: Thomas Papathymiopoulos <thomaspapathimiopoylos@gmail.com>
License: MIT License
Project-URL: Homepage, https://github.com/Thomatous/Chartops
Keywords: Chartops
Classifier: Intended Audience :: Developers
Classifier: License :: OSI Approved :: MIT License
Classifier: Natural Language :: English
Classifier: Programming Language :: Python :: 3.8
Classifier: Programming Language :: Python :: 3.9
Classifier: Programming Language :: Python :: 3.10
Classifier: Programming Language :: Python :: 3.11
Classifier: Programming Language :: Python :: 3.12
Requires-Python: >=3.8
License-File: LICENSE
Requires-Dist: folium
Requires-Dist: geopandas
Requires-Dist: ipyleaflet
Requires-Dist: ipywidgets
Requires-Dist: localtileserver
Requires-Dist: matplotlib
Requires-Dist: numpy
Provides-Extra: all
Requires-Dist: Chartops[extra]; extra == "all"
Provides-Extra: extra
Requires-Dist: pandas; extra == "extra"
Dynamic: license-file
